service_cat_creator_app-0.1.0.dist-info/licenses/LICENSE.md
servicenow_agent/__init__.py
servicenow_agent/server.py
service_cat_creator_app-0.1.0.dist-info/METADATA
service_cat_creator_app-0.1.0.dist-info/WHEEL
service_cat_creator_app-0.1.0.dist-info/entry_points.txt
service_cat_creator_app-0.1.0.dist-info/top_level.txt
service_cat_creator_app-0.1.0.dist-info/RECORD
