Metadata-Version: 2.4
Name: service-cat-creator-app
Version: 0.1.0
Summary: This tool allows you to create a service catalog by simple prompts, then generate json file of specified format then it checks whether the record of this type is already present in servicenow instance or not if not it creates a new record in the instance.
Author: Divya Shah
Maintainer-email: Divya Shah <shah.divya.2206@gmail.com>
License: Apache-2.0 with Additional Restrictions
Classifier: Development Status :: 4 - Beta
Classifier: Intended Audience :: Developers
Classifier: License :: OSI Approved :: Apache Software License
Classifier: Programming Language :: Python :: 3
Classifier: Programming Language :: Python :: 3.10
Classifier: Programming Language :: Python :: 3.11
Classifier: Programming Language :: Python :: 3.12
Classifier: Programming Language :: Python :: 3.13
Requires-Python: >=3.10
License-File: LICENSE.md
Requires-Dist: click>=8.1.3
Requires-Dist: flask>=2.2.2
Requires-Dist: httpx>=0.23.0
Requires-Dist: python-dotenv>=0.21.0
Requires-Dist: google-generativeai>=0.3.0
Dynamic: license-file
